{"nodes": [{"id": "06_build_fts_index", "label": "Step 06: Build FTS5 Index (titles + chunks, bilingual)", "file_type": "code", "source_file": "scripts/06-build-fts.ts", "source_location": null, "source_url": null, "captured_at": null, "author": null, "contributor": null}, {"id": "concept_title_fts_table", "label": "Table: title_fts (FTS5 titles, unicode61 remove_diacritics)", "file_type": "code", "source_file": "scripts/06-build-fts.ts", "source_location": null, "source_url": null, "captured_at": null, "author": null, "contributor": null}, {"id": "concept_segment_fts_table", "label": "Table: segment_fts (FTS5 chunks)", "file_type": "code", "source_file": "scripts/06-build-fts.ts", "source_location": null, "source_url": null, "captured_at": null, "author": null, "contributor": null}], "edges": [{"source": "05_ingest_graph_concepts", "target": "06_build_fts_index", "relation": "shares_data_with", "confidence": "INFERRED", "confidence_score": 0.85, "source_file": "scripts/06-build-fts.ts", "source_location": null, "weight": 1.0}, {"source": "06_build_fts_index", "target": "_env_dotenv_loader", "relation": "calls", "confidence": "EXTRACTED", "confidence_score": 1.0, "source_file": "scripts/06-build-fts.ts", "source_location": null, "weight": 1.0}, {"source": "06_build_fts_index", "target": "lib_db_module", "relation": "calls", "confidence": "EXTRACTED", "confidence_score": 1.0, "source_file": "scripts/06-build-fts.ts", "source_location": null, "weight": 1.0}, {"source": "06_build_fts_index", "target": "concept_title_fts_table", "relation": "implements", "confidence": "EXTRACTED", "confidence_score": 1.0, "source_file": "scripts/06-build-fts.ts", "source_location": null, "weight": 1.0}, {"source": "06_build_fts_index", "target": "concept_segment_fts_table", "relation": "implements", "confidence": "EXTRACTED", "confidence_score": 1.0, "source_file": "scripts/06-build-fts.ts", "source_location": null, "weight": 1.0}, {"source": "06_build_fts_index", "target": "concept_chunks_table", "relation": "shares_data_with", "confidence": "EXTRACTED", "confidence_score": 1.0, "source_file": "scripts/06-build-fts.ts", "source_location": null, "weight": 1.0}], "hyperedges": []}